mara_dbt/__init__.py
mara_dbt/cli.py
mara_dbt/commands.py
mara_dbt/config.py
mara_dbt/integration.py
mara_dbt/setup.py
mara_dbt-0.2.0.dist-info/LICENSE
mara_dbt-0.2.0.dist-info/METADATA
mara_dbt-0.2.0.dist-info/WHEEL
mara_dbt-0.2.0.dist-info/top_level.txt
mara_dbt-0.2.0.dist-info/RECORD
