Metadata-Version: 2.1
Name: mara-dbt
Version: 0.2.0
Summary: dbt integration into the mara framework
Home-page: https://github.com/mara/mara-dbt
Author: Mara contributors
License: MIT
Requires-Python: >=3.6.2
License-File: LICENSE
Requires-Dist: click
Requires-Dist: mara-pipelines (>=3.1.0)
Requires-Dist: mara-db (>=4.7.1)
Requires-Dist: mara-page (>=1.3.0)
Requires-Dist: PyYAML (>=5.4.1)
Provides-Extra: dbt-cloud
Requires-Dist: dbt-cloud-cli (>=0.7.2) ; extra == 'dbt-cloud'
